lightbulb/__init__.py
lightbulb/__main__.py
lightbulb/client.py
lightbulb/config.py
lightbulb/context.py
lightbulb/di.py
lightbulb/exceptions.py
lightbulb/features.py
lightbulb/loaders.py
lightbulb/localization.py
lightbulb/metaparams.json
lightbulb/py.typed
lightbulb/tasks.py
lightbulb/utils.py
lightbulb/commands/__init__.py
lightbulb/commands/commands.py
lightbulb/commands/execution.py
lightbulb/commands/groups.py
lightbulb/commands/options.py
lightbulb/commands/utils.py
lightbulb/components/__init__.py
lightbulb/components/base.py
lightbulb/components/menus.py
lightbulb/components/modals.py
lightbulb/internal/__init__.py
lightbulb/internal/constants.py
lightbulb/internal/marker.py
lightbulb/internal/sync.py
lightbulb/internal/types.py
lightbulb/internal/utils.py
lightbulb/prefab/__init__.py
lightbulb/prefab/checks.py
lightbulb/prefab/concurrency.py
lightbulb/prefab/cooldowns.py
hikari_lightbulb-3.2.3.dist-info/licenses/LICENSE
hikari_lightbulb-3.2.3.dist-info/WHEEL
hikari_lightbulb-3.2.3.dist-info/METADATA
hikari_lightbulb-3.2.3.dist-info/RECORD
