Metadata-Version: 2.4
Name: hikari-lightbulb
Version: 3.2.3
Summary: A simple, elegant, and powerful command handler for Hikari.
Keywords: hikari
Author-email: tandemdude <tandemdude1@gmail.com>
Requires-Python: >=3.10.0,<3.15
Classifier: Development Status :: 5 - Production/Stable
Classifier: License :: OSI Approved :: MIT License
Classifier: Framework :: AsyncIO
Classifier: Intended Audience :: Developers
Classifier: Natural Language :: English
Classifier: Topic :: Software Development :: Libraries :: Python Modules
Classifier: Programming Language :: Python :: 3.10
Classifier: Programming Language :: Python :: 3.11
Classifier: Programming Language :: Python :: 3.12
Classifier: Programming Language :: Python :: 3.13
Classifier: Programming Language :: Python :: Implementation :: CPython
Classifier: Programming Language :: Python :: 3 :: Only
Classifier: Topic :: Software Development :: Libraries
Classifier: Topic :: Software Development :: Libraries :: Application Frameworks
Classifier: Topic :: Software Development :: Libraries :: Python Modules
Classifier: Typing :: Typed
License-File: LICENSE
Requires-Dist: hikari~=2.5.0
Requires-Dist: async-timeout>=4, <6
Requires-Dist: linkd>=0.2.1
Requires-Dist: confspec>=0.0.1
Requires-Dist: typing-extensions>=4
Requires-Dist: croniter>=3.0.3, <7 ; extra == "crontrigger"
Requires-Dist: nox==2025.11.12 ; extra == "dev"
Requires-Dist: towncrier==25.8.0 ; extra == "dev-changelog"
Requires-Dist: sphinx>=8.0.2, <9 ; extra == "dev-docs"
Requires-Dist: furo==2025.12.19 ; extra == "dev-docs"
Requires-Dist: myst-parser>=4.0.0, <5 ; extra == "dev-docs"
Requires-Dist: sphinx-copybutton>=0.5.2, <1 ; extra == "dev-docs"
Requires-Dist: sphinx-inline-tabs==2025.12.21.14 ; extra == "dev-docs"
Requires-Dist: sphinx_design>=0.6.0, <1 ; extra == "dev-docs"
Requires-Dist: sphinx-prompt>=1.8.0, <2 ; extra == "dev-docs"
Requires-Dist: sphinx-notfound-page>=1.0.2, <2 ; extra == "dev-docs"
Requires-Dist: sphinxext-opengraph>=0.9.1, <1 ; extra == "dev-docs"
Requires-Dist: sphinxcontrib-mermaid>=0.9.2, <2 ; extra == "dev-docs"
Requires-Dist: ruff==0.14.10 ; extra == "dev-format"
Requires-Dist: flit==3.12.0 ; extra == "dev-release"
Requires-Dist: slotscheck>=0.19.0, <1 ; extra == "dev-slotscheck"
Requires-Dist: pytest>=8.3.2, <10 ; extra == "dev-test"
Requires-Dist: pytest-asyncio>=0.23.8, <1.4 ; extra == "dev-test"
Requires-Dist: pytest-cov>=5.0.0, <8 ; extra == "dev-test"
Requires-Dist: pytest-randomly>=3.15.0, <5 ; extra == "dev-test"
Requires-Dist: pyright==1.1.407 ; extra == "dev-typecheck"
Requires-Dist: typing-extensions>=4.12.2, <5 ; extra == "dev-typecheck"
Requires-Dist: types-polib>=1.2.0.20240327, <2 ; extra == "dev-typecheck"
Requires-Dist: types-croniter>=3.0.0.20240727, <6 ; extra == "dev-typecheck"
Requires-Dist: polib>=1.2.0, <2 ; extra == "localization"
Project-URL: Changelog, https://hikari-lightbulb.readthedocs.io/en/latest/changelog.html
Project-URL: Documentation, https://hikari-lightbulb.readthedocs.io/en/latest/
Project-URL: Homepage, https://github.com/tandemdude/hikari-lightbulb
Project-URL: Repository, https://github.com/tandemdude/hikari-lightbulb
Provides-Extra: crontrigger
Provides-Extra: dev
Provides-Extra: dev-changelog
Provides-Extra: dev-docs
Provides-Extra: dev-format
Provides-Extra: dev-release
Provides-Extra: dev-slotscheck
Provides-Extra: dev-test
Provides-Extra: dev-typecheck
Provides-Extra: localization
